sparseSEM.cpython-310-darwin.so
sparseSEM/__init__.py
sparseSEM/elasticNetSML.py
sparseSEM/elasticNetSMLcv.py
sparseSEM/elasticNetSMLpoint.py
sparseSEM/enSEM_STS.py
sparseSEM/loadSEMlib.py
sparseSEM/sparseSEM.cpython-310-darwin.so
sparseSEM/src/lassoSEM.c
sparseSEM/src/lassoSEM.h
sparseSEM/src/lassoSMLv11beta.c
sparseSEM-2.1.dist-info/METADATA
sparseSEM-2.1.dist-info/WHEEL
sparseSEM-2.1.dist-info/top_level.txt
sparseSEM-2.1.dist-info/RECORD
